[
  {
    "log_path": "eval_logs/2026-06-03_v12_candidate_mcts32_debug_vs_rapfi_g2.log",
    "game_number": 1,
    "black": "neural_v12_debug",
    "white": "rapfi_fast",
    "game_result": "0-1",
    "loss_reason": "White win by five connection",
    "rapfi_bestlines": [
      "E5",
      "F5",
      "F6",
      "F7",
      "G6",
      "G8",
      "D6",
      "F4 F3",
      "G3 H2"
    ],
    "final_neural_moves_near_end": [
      "4:6,4",
      "6:6,6",
      "8:5,7",
      "10:4,7",
      "12:6,8",
      "14:4,5",
      "16:5,2",
      "18:7,1"
    ],
    "debug_decisions": [
      {
        "line_no": 73,
        "engine": "neural_v12_debug",
        "side_to_move": "black",
        "move_count": 0,
        "player": 1,
        "sims": 32,
        "mode": "mcts_safe",
        "value": 0.291793,
        "direct": "7,7",
        "policy_safety": "7,7",
        "mcts_raw": "7,7",
        "mcts_safety": "7,7",
        "final": "7,7",
        "previous_rapfi_bestline": "",
        "next_rapfi_bestline": "E5",
        "debug_decision_line": "engine neural_v12_debug output debug:_DECISION mode=mcts_safe move_count=0 player=1 sims=32 value=0.291793 direct=(x=7,y=7,row=7,col=7) policy_safety=(x=7,y=7,row=7,col=7) mcts_raw=(x=7,y=7,row=7,col=7) mcts_safety=(x=7,y=7,row=7,col=7) final=(x=7,y=7,row=7,col=7)"
      },
      {
        "line_no": 110,
        "engine": "neural_v12_debug",
        "side_to_move": "black",
        "move_count": 2,
        "player": 1,
        "sims": 32,
        "mode": "mcts_safe",
        "value": 0.196545,
        "direct": "4,6",
        "policy_safety": "4,6",
        "mcts_raw": "4,6",
        "mcts_safety": "4,6",
        "final": "4,6",
        "previous_rapfi_bestline": "E5",
        "next_rapfi_bestline": "F5",
        "debug_decision_line": "engine neural_v12_debug output debug:_DECISION mode=mcts_safe move_count=2 player=1 sims=32 value=0.196545 direct=(x=4,y=6,row=6,col=4) policy_safety=(x=4,y=6,row=6,col=4) mcts_raw=(x=4,y=6,row=6,col=4) mcts_safety=(x=4,y=6,row=6,col=4) final=(x=4,y=6,row=6,col=4)"
      },
      {
        "line_no": 147,
        "engine": "neural_v12_debug",
        "side_to_move": "black",
        "move_count": 4,
        "player": 1,
        "sims": 32,
        "mode": "mcts_safe",
        "value": -0.106744,
        "direct": "6,4",
        "policy_safety": "6,4",
        "mcts_raw": "6,4",
        "mcts_safety": "6,4",
        "final": "6,4",
        "previous_rapfi_bestline": "F5",
        "next_rapfi_bestline": "F6",
        "debug_decision_line": "engine neural_v12_debug output debug:_DECISION mode=mcts_safe move_count=4 player=1 sims=32 value=-0.106744 direct=(x=6,y=4,row=4,col=6) policy_safety=(x=6,y=4,row=4,col=6) mcts_raw=(x=6,y=4,row=4,col=6) mcts_safety=(x=6,y=4,row=4,col=6) final=(x=6,y=4,row=4,col=6)"
      },
      {
        "line_no": 184,
        "engine": "neural_v12_debug",
        "side_to_move": "black",
        "move_count": 6,
        "player": 1,
        "sims": 32,
        "mode": "mcts_safe",
        "value": 0.0194,
        "direct": "6,6",
        "policy_safety": "6,6",
        "mcts_raw": "6,6",
        "mcts_safety": "6,6",
        "final": "6,6",
        "previous_rapfi_bestline": "F6",
        "next_rapfi_bestline": "F7",
        "debug_decision_line": "engine neural_v12_debug output debug:_DECISION mode=mcts_safe move_count=6 player=1 sims=32 value=0.019400 direct=(x=6,y=6,row=6,col=6) policy_safety=(x=6,y=6,row=6,col=6) mcts_raw=(x=6,y=6,row=6,col=6) mcts_safety=(x=6,y=6,row=6,col=6) final=(x=6,y=6,row=6,col=6)"
      },
      {
        "line_no": 221,
        "engine": "neural_v12_debug",
        "side_to_move": "black",
        "move_count": 8,
        "player": 1,
        "sims": 32,
        "mode": "mcts_safe",
        "value": 0.536618,
        "direct": "5,7",
        "policy_safety": "5,7",
        "mcts_raw": "5,7",
        "mcts_safety": "5,7",
        "final": "5,7",
        "previous_rapfi_bestline": "F7",
        "next_rapfi_bestline": "G6",
        "debug_decision_line": "engine neural_v12_debug output debug:_DECISION mode=mcts_safe move_count=8 player=1 sims=32 value=0.536618 direct=(x=5,y=7,row=7,col=5) policy_safety=(x=5,y=7,row=7,col=5) mcts_raw=(x=5,y=7,row=7,col=5) mcts_safety=(x=5,y=7,row=7,col=5) final=(x=5,y=7,row=7,col=5)"
      },
      {
        "line_no": 258,
        "engine": "neural_v12_debug",
        "side_to_move": "black",
        "move_count": 10,
        "player": 1,
        "sims": 32,
        "mode": "mcts_safe",
        "value": 0.468122,
        "direct": "7,6",
        "policy_safety": "7,6",
        "mcts_raw": "4,7",
        "mcts_safety": "4,7",
        "final": "4,7",
        "previous_rapfi_bestline": "G6",
        "next_rapfi_bestline": "G8",
        "debug_decision_line": "engine neural_v12_debug output debug:_DECISION mode=mcts_safe move_count=10 player=1 sims=32 value=0.468122 direct=(x=7,y=6,row=6,col=7) policy_safety=(x=7,y=6,row=6,col=7) mcts_raw=(x=4,y=7,row=7,col=4) mcts_safety=(x=4,y=7,row=7,col=4) final=(x=4,y=7,row=7,col=4)"
      },
      {
        "line_no": 295,
        "engine": "neural_v12_debug",
        "side_to_move": "black",
        "move_count": 12,
        "player": 1,
        "sims": 32,
        "mode": "mcts_safe",
        "value": 0.680296,
        "direct": "6,8",
        "policy_safety": "6,8",
        "mcts_raw": "6,8",
        "mcts_safety": "6,8",
        "final": "6,8",
        "previous_rapfi_bestline": "G8",
        "next_rapfi_bestline": "D6",
        "debug_decision_line": "engine neural_v12_debug output debug:_DECISION mode=mcts_safe move_count=12 player=1 sims=32 value=0.680296 direct=(x=6,y=8,row=8,col=6) policy_safety=(x=6,y=8,row=8,col=6) mcts_raw=(x=6,y=8,row=8,col=6) mcts_safety=(x=6,y=8,row=8,col=6) final=(x=6,y=8,row=8,col=6)"
      },
      {
        "line_no": 332,
        "engine": "neural_v12_debug",
        "side_to_move": "black",
        "move_count": 14,
        "player": 1,
        "sims": 32,
        "mode": "mcts_safe",
        "value": 0.478734,
        "direct": "4,5",
        "policy_safety": "4,5",
        "mcts_raw": "4,5",
        "mcts_safety": "4,5",
        "final": "4,5",
        "previous_rapfi_bestline": "D6",
        "next_rapfi_bestline": "F4 F3",
        "debug_decision_line": "engine neural_v12_debug output debug:_DECISION mode=mcts_safe move_count=14 player=1 sims=32 value=0.478734 direct=(x=4,y=5,row=5,col=4) policy_safety=(x=4,y=5,row=5,col=4) mcts_raw=(x=4,y=5,row=5,col=4) mcts_safety=(x=4,y=5,row=5,col=4) final=(x=4,y=5,row=5,col=4)"
      },
      {
        "line_no": 369,
        "engine": "neural_v12_debug",
        "side_to_move": "black",
        "move_count": 16,
        "player": 1,
        "sims": 32,
        "mode": "mcts_safe",
        "value": 0.757017,
        "direct": "3,7",
        "policy_safety": "5,2",
        "mcts_raw": "5,2",
        "mcts_safety": "5,2",
        "final": "5,2",
        "previous_rapfi_bestline": "F4 F3",
        "next_rapfi_bestline": "G3 H2",
        "debug_decision_line": "engine neural_v12_debug output debug:_DECISION mode=mcts_safe move_count=16 player=1 sims=32 value=0.757017 direct=(x=3,y=7,row=7,col=3) policy_safety=(x=5,y=2,row=2,col=5) mcts_raw=(x=5,y=2,row=2,col=5) mcts_safety=(x=5,y=2,row=2,col=5) final=(x=5,y=2,row=2,col=5)"
      },
      {
        "line_no": 406,
        "engine": "neural_v12_debug",
        "side_to_move": "black",
        "move_count": 18,
        "player": 1,
        "sims": 32,
        "mode": "mcts_safe",
        "value": 0.695656,
        "direct": "7,1",
        "policy_safety": "7,1",
        "mcts_raw": "7,1",
        "mcts_safety": "7,1",
        "final": "7,1",
        "previous_rapfi_bestline": "G3 H2",
        "next_rapfi_bestline": "",
        "debug_decision_line": "engine neural_v12_debug output debug:_DECISION mode=mcts_safe move_count=18 player=1 sims=32 value=0.695656 direct=(x=7,y=1,row=1,col=7) policy_safety=(x=7,y=1,row=1,col=7) mcts_raw=(x=7,y=1,row=1,col=7) mcts_safety=(x=7,y=1,row=1,col=7) final=(x=7,y=1,row=1,col=7)"
      }
    ]
  },
  {
    "log_path": "eval_logs/2026-06-03_v12_candidate_mcts32_debug_vs_rapfi_g2.log",
    "game_number": 2,
    "black": "rapfi_fast",
    "white": "neural_v12_debug",
    "game_result": "1-0",
    "loss_reason": "Black win by five connection",
    "rapfi_bestlines": [
      "G9",
      "G8",
      "F8",
      "E7",
      "H9",
      "J9",
      "I10",
      "I7",
      "J11 K12 H10 I11",
      "H10 I11",
      "E8 D8",
      "E9",
      "D9 F9",
      "E5 E6",
      "J10",
      "J8 J12"
    ],
    "final_neural_moves_near_end": [
      "19:10,11",
      "21:8,10",
      "23:3,7",
      "25:4,9",
      "27:5,8",
      "29:4,5",
      "31:10,9",
      "33:9,6"
    ],
    "debug_decisions": [
      {
        "line_no": 478,
        "engine": "neural_v12_debug",
        "side_to_move": "white",
        "move_count": 1,
        "player": 1,
        "sims": 32,
        "mode": "mcts_safe",
        "value": -0.883943,
        "direct": "7,6",
        "policy_safety": "7,6",
        "mcts_raw": "7,6",
        "mcts_safety": "7,6",
        "final": "7,6",
        "previous_rapfi_bestline": "",
        "next_rapfi_bestline": "G9",
        "debug_decision_line": "engine neural_v12_debug output debug:_DECISION mode=mcts_safe move_count=1 player=1 sims=32 value=-0.883943 direct=(x=7,y=6,row=6,col=7) policy_safety=(x=7,y=6,row=6,col=7) mcts_raw=(x=7,y=6,row=6,col=7) mcts_safety=(x=7,y=6,row=6,col=7) final=(x=7,y=6,row=6,col=7)"
      },
      {
        "line_no": 515,
        "engine": "neural_v12_debug",
        "side_to_move": "white",
        "move_count": 3,
        "player": 1,
        "sims": 32,
        "mode": "mcts_safe",
        "value": -0.499193,
        "direct": "5,9",
        "policy_safety": "5,9",
        "mcts_raw": "5,9",
        "mcts_safety": "5,9",
        "final": "5,9",
        "previous_rapfi_bestline": "G9",
        "next_rapfi_bestline": "G8",
        "debug_decision_line": "engine neural_v12_debug output debug:_DECISION mode=mcts_safe move_count=3 player=1 sims=32 value=-0.499193 direct=(x=5,y=9,row=9,col=5) policy_safety=(x=5,y=9,row=9,col=5) mcts_raw=(x=5,y=9,row=9,col=5) mcts_safety=(x=5,y=9,row=9,col=5) final=(x=5,y=9,row=9,col=5)"
      },
      {
        "line_no": 552,
        "engine": "neural_v12_debug",
        "side_to_move": "white",
        "move_count": 5,
        "player": 1,
        "sims": 32,
        "mode": "mcts_safe",
        "value": -0.780325,
        "direct": "6,6",
        "policy_safety": "6,6",
        "mcts_raw": "6,6",
        "mcts_safety": "6,6",
        "final": "6,6",
        "previous_rapfi_bestline": "G8",
        "next_rapfi_bestline": "F8",
        "debug_decision_line": "engine neural_v12_debug output debug:_DECISION mode=mcts_safe move_count=5 player=1 sims=32 value=-0.780325 direct=(x=6,y=6,row=6,col=6) policy_safety=(x=6,y=6,row=6,col=6) mcts_raw=(x=6,y=6,row=6,col=6) mcts_safety=(x=6,y=6,row=6,col=6) final=(x=6,y=6,row=6,col=6)"
      },
      {
        "line_no": 589,
        "engine": "neural_v12_debug",
        "side_to_move": "white",
        "move_count": 7,
        "player": 1,
        "sims": 32,
        "mode": "mcts_safe",
        "value": -0.788462,
        "direct": "8,7",
        "policy_safety": "8,7",
        "mcts_raw": "8,7",
        "mcts_safety": "8,7",
        "final": "8,7",
        "previous_rapfi_bestline": "F8",
        "next_rapfi_bestline": "E7",
        "debug_decision_line": "engine neural_v12_debug output debug:_DECISION mode=mcts_safe move_count=7 player=1 sims=32 value=-0.788462 direct=(x=8,y=7,row=7,col=8) policy_safety=(x=8,y=7,row=7,col=8) mcts_raw=(x=8,y=7,row=7,col=8) mcts_safety=(x=8,y=7,row=7,col=8) final=(x=8,y=7,row=7,col=8)"
      },
      {
        "line_no": 626,
        "engine": "neural_v12_debug",
        "side_to_move": "white",
        "move_count": 9,
        "player": 1,
        "sims": 32,
        "mode": "mcts_safe",
        "value": -0.767084,
        "direct": "3,5",
        "policy_safety": "3,5",
        "mcts_raw": "3,5",
        "mcts_safety": "3,5",
        "final": "3,5",
        "previous_rapfi_bestline": "E7",
        "next_rapfi_bestline": "H9",
        "debug_decision_line": "engine neural_v12_debug output debug:_DECISION mode=mcts_safe move_count=9 player=1 sims=32 value=-0.767084 direct=(x=3,y=5,row=5,col=3) policy_safety=(x=3,y=5,row=5,col=3) mcts_raw=(x=3,y=5,row=5,col=3) mcts_safety=(x=3,y=5,row=5,col=3) final=(x=3,y=5,row=5,col=3)"
      },
      {
        "line_no": 663,
        "engine": "neural_v12_debug",
        "side_to_move": "white",
        "move_count": 11,
        "player": 1,
        "sims": 32,
        "mode": "mcts_safe",
        "value": -0.881746,
        "direct": "5,6",
        "policy_safety": "5,6",
        "mcts_raw": "5,6",
        "mcts_safety": "5,6",
        "final": "5,6",
        "previous_rapfi_bestline": "H9",
        "next_rapfi_bestline": "J9",
        "debug_decision_line": "engine neural_v12_debug output debug:_DECISION mode=mcts_safe move_count=11 player=1 sims=32 value=-0.881746 direct=(x=5,y=6,row=6,col=5) policy_safety=(x=5,y=6,row=6,col=5) mcts_raw=(x=5,y=6,row=6,col=5) mcts_safety=(x=5,y=6,row=6,col=5) final=(x=5,y=6,row=6,col=5)"
      },
      {
        "line_no": 700,
        "engine": "neural_v12_debug",
        "side_to_move": "white",
        "move_count": 13,
        "player": 1,
        "sims": 32,
        "mode": "mcts_safe",
        "value": -0.686766,
        "direct": "8,8",
        "policy_safety": "8,8",
        "mcts_raw": "8,8",
        "mcts_safety": "8,8",
        "final": "8,8",
        "previous_rapfi_bestline": "J9",
        "next_rapfi_bestline": "I10",
        "debug_decision_line": "engine neural_v12_debug output debug:_DECISION mode=mcts_safe move_count=13 player=1 sims=32 value=-0.686766 direct=(x=8,y=8,row=8,col=8) policy_safety=(x=8,y=8,row=8,col=8) mcts_raw=(x=8,y=8,row=8,col=8) mcts_safety=(x=8,y=8,row=8,col=8) final=(x=8,y=8,row=8,col=8)"
      },
      {
        "line_no": 737,
        "engine": "neural_v12_debug",
        "side_to_move": "white",
        "move_count": 15,
        "player": 1,
        "sims": 32,
        "mode": "mcts_safe",
        "value": -0.104294,
        "direct": "7,10",
        "policy_safety": "7,10",
        "mcts_raw": "7,10",
        "mcts_safety": "7,10",
        "final": "7,10",
        "previous_rapfi_bestline": "I10",
        "next_rapfi_bestline": "I7",
        "debug_decision_line": "engine neural_v12_debug output debug:_DECISION mode=mcts_safe move_count=15 player=1 sims=32 value=-0.104294 direct=(x=7,y=10,row=10,col=7) policy_safety=(x=7,y=10,row=10,col=7) mcts_raw=(x=7,y=10,row=10,col=7) mcts_safety=(x=7,y=10,row=10,col=7) final=(x=7,y=10,row=10,col=7)"
      },
      {
        "line_no": 774,
        "engine": "neural_v12_debug",
        "side_to_move": "white",
        "move_count": 17,
        "player": 1,
        "sims": 32,
        "mode": "mcts_safe",
        "value": -0.504522,
        "direct": "9,5",
        "policy_safety": "9,5",
        "mcts_raw": "9,5",
        "mcts_safety": "9,5",
        "final": "9,5",
        "previous_rapfi_bestline": "I7",
        "next_rapfi_bestline": "J11 K12 H10 I11",
        "debug_decision_line": "engine neural_v12_debug output debug:_DECISION mode=mcts_safe move_count=17 player=1 sims=32 value=-0.504522 direct=(x=9,y=5,row=5,col=9) policy_safety=(x=9,y=5,row=5,col=9) mcts_raw=(x=9,y=5,row=5,col=9) mcts_safety=(x=9,y=5,row=5,col=9) final=(x=9,y=5,row=5,col=9)"
      },
      {
        "line_no": 811,
        "engine": "neural_v12_debug",
        "side_to_move": "white",
        "move_count": 19,
        "player": 1,
        "sims": 32,
        "mode": "mcts_safe",
        "value": -0.650949,
        "direct": "9,9",
        "policy_safety": "10,11",
        "mcts_raw": "10,11",
        "mcts_safety": "10,11",
        "final": "10,11",
        "previous_rapfi_bestline": "J11 K12 H10 I11",
        "next_rapfi_bestline": "H10 I11",
        "debug_decision_line": "engine neural_v12_debug output debug:_DECISION mode=mcts_safe move_count=19 player=1 sims=32 value=-0.650949 direct=(x=9,y=9,row=9,col=9) policy_safety=(x=10,y=11,row=11,col=10) mcts_raw=(x=10,y=11,row=11,col=10) mcts_safety=(x=10,y=11,row=11,col=10) final=(x=10,y=11,row=11,col=10)"
      },
      {
        "line_no": 848,
        "engine": "neural_v12_debug",
        "side_to_move": "white",
        "move_count": 21,
        "player": 1,
        "sims": 32,
        "mode": "mcts_safe",
        "value": -0.391579,
        "direct": "9,9",
        "policy_safety": "8,10",
        "mcts_raw": "8,10",
        "mcts_safety": "8,10",
        "final": "8,10",
        "previous_rapfi_bestline": "H10 I11",
        "next_rapfi_bestline": "E8 D8",
        "debug_decision_line": "engine neural_v12_debug output debug:_DECISION mode=mcts_safe move_count=21 player=1 sims=32 value=-0.391579 direct=(x=9,y=9,row=9,col=9) policy_safety=(x=8,y=10,row=10,col=8) mcts_raw=(x=8,y=10,row=10,col=8) mcts_safety=(x=8,y=10,row=10,col=8) final=(x=8,y=10,row=10,col=8)"
      },
      {
        "line_no": 885,
        "engine": "neural_v12_debug",
        "side_to_move": "white",
        "move_count": 23,
        "player": 1,
        "sims": 32,
        "mode": "mcts_safe",
        "value": -0.460754,
        "direct": "3,7",
        "policy_safety": "3,7",
        "mcts_raw": "3,7",
        "mcts_safety": "3,7",
        "final": "3,7",
        "previous_rapfi_bestline": "E8 D8",
        "next_rapfi_bestline": "E9",
        "debug_decision_line": "engine neural_v12_debug output debug:_DECISION mode=mcts_safe move_count=23 player=1 sims=32 value=-0.460754 direct=(x=3,y=7,row=7,col=3) policy_safety=(x=3,y=7,row=7,col=3) mcts_raw=(x=3,y=7,row=7,col=3) mcts_safety=(x=3,y=7,row=7,col=3) final=(x=3,y=7,row=7,col=3)"
      },
      {
        "line_no": 922,
        "engine": "neural_v12_debug",
        "side_to_move": "white",
        "move_count": 25,
        "player": 1,
        "sims": 32,
        "mode": "mcts_safe",
        "value": -0.456023,
        "direct": "5,8",
        "policy_safety": "4,9",
        "mcts_raw": "5,8",
        "mcts_safety": "4,9",
        "final": "4,9",
        "previous_rapfi_bestline": "E9",
        "next_rapfi_bestline": "D9 F9",
        "debug_decision_line": "engine neural_v12_debug output debug:_DECISION mode=mcts_safe move_count=25 player=1 sims=32 value=-0.456023 direct=(x=5,y=8,row=8,col=5) policy_safety=(x=4,y=9,row=9,col=4) mcts_raw=(x=5,y=8,row=8,col=5) mcts_safety=(x=4,y=9,row=9,col=4) final=(x=4,y=9,row=9,col=4)"
      },
      {
        "line_no": 959,
        "engine": "neural_v12_debug",
        "side_to_move": "white",
        "move_count": 27,
        "player": 1,
        "sims": 32,
        "mode": "mcts_safe",
        "value": -0.61592,
        "direct": "5,8",
        "policy_safety": "5,8",
        "mcts_raw": "5,8",
        "mcts_safety": "5,8",
        "final": "5,8",
        "previous_rapfi_bestline": "D9 F9",
        "next_rapfi_bestline": "E5 E6",
        "debug_decision_line": "engine neural_v12_debug output debug:_DECISION mode=mcts_safe move_count=27 player=1 sims=32 value=-0.615920 direct=(x=5,y=8,row=8,col=5) policy_safety=(x=5,y=8,row=8,col=5) mcts_raw=(x=5,y=8,row=8,col=5) mcts_safety=(x=5,y=8,row=8,col=5) final=(x=5,y=8,row=8,col=5)"
      },
      {
        "line_no": 996,
        "engine": "neural_v12_debug",
        "side_to_move": "white",
        "move_count": 29,
        "player": 1,
        "sims": 32,
        "mode": "mcts_safe",
        "value": -0.666071,
        "direct": "4,5",
        "policy_safety": "4,5",
        "mcts_raw": "4,5",
        "mcts_safety": "4,5",
        "final": "4,5",
        "previous_rapfi_bestline": "E5 E6",
        "next_rapfi_bestline": "J10",
        "debug_decision_line": "engine neural_v12_debug output debug:_DECISION mode=mcts_safe move_count=29 player=1 sims=32 value=-0.666071 direct=(x=4,y=5,row=5,col=4) policy_safety=(x=4,y=5,row=5,col=4) mcts_raw=(x=4,y=5,row=5,col=4) mcts_safety=(x=4,y=5,row=5,col=4) final=(x=4,y=5,row=5,col=4)"
      },
      {
        "line_no": 1033,
        "engine": "neural_v12_debug",
        "side_to_move": "white",
        "move_count": 31,
        "player": 1,
        "sims": 32,
        "mode": "mcts_safe",
        "value": -0.754536,
        "direct": "10,7",
        "policy_safety": "10,9",
        "mcts_raw": "3,9",
        "mcts_safety": "10,9",
        "final": "10,9",
        "previous_rapfi_bestline": "J10",
        "next_rapfi_bestline": "J8 J12",
        "debug_decision_line": "engine neural_v12_debug output debug:_DECISION mode=mcts_safe move_count=31 player=1 sims=32 value=-0.754536 direct=(x=10,y=7,row=7,col=10) policy_safety=(x=10,y=9,row=9,col=10) mcts_raw=(x=3,y=9,row=9,col=3) mcts_safety=(x=10,y=9,row=9,col=10) final=(x=10,y=9,row=9,col=10)"
      },
      {
        "line_no": 1070,
        "engine": "neural_v12_debug",
        "side_to_move": "white",
        "move_count": 33,
        "player": 1,
        "sims": 32,
        "mode": "mcts_safe",
        "value": -0.768495,
        "direct": "9,6",
        "policy_safety": "9,6",
        "mcts_raw": "9,6",
        "mcts_safety": "9,6",
        "final": "9,6",
        "previous_rapfi_bestline": "J8 J12",
        "next_rapfi_bestline": "",
        "debug_decision_line": "engine neural_v12_debug output debug:_DECISION mode=mcts_safe move_count=33 player=1 sims=32 value=-0.768495 direct=(x=9,y=6,row=6,col=9) policy_safety=(x=9,y=6,row=6,col=9) mcts_raw=(x=9,y=6,row=6,col=9) mcts_safety=(x=9,y=6,row=6,col=9) final=(x=9,y=6,row=6,col=9)"
      }
    ]
  }
]
